yu_twinkle/__init__.py
yu_twinkle/func_bin.py
yu_twinkle/func_exotethys.py
yu_twinkle/func_fit.py
yu_twinkle/func_pylc.py
yu_twinkle/func_stardrive.py
yu_twinkle/func_view_fitting.py
yu_twinkle/func_view_lc.py
yu_twinkle-0.0.2.dist-info/METADATA
yu_twinkle-0.0.2.dist-info/WHEEL
yu_twinkle-0.0.2.dist-info/top_level.txt
yu_twinkle-0.0.2.dist-info/RECORD
