Metadata-Version: 2.1
Name: yu-twinkle
Version: 0.0.2
Summary: Twinkle project functions.
Home-page: https://github.com/wmjx691/yu_twinkle
Author: Kevin Yu
Author-email: wmjx691@gmail.com
Classifier: Programming Language :: Python :: 3
Classifier: License :: OSI Approved :: MIT License
Classifier: Operating System :: OS Independent
Requires-Python: >=3.6
